meinkonfig/__init__.py
meinkonfig/konfig.py
meinkonfig-0.1.0.dist-info/METADATA
meinkonfig-0.1.0.dist-info/WHEEL
meinkonfig-0.1.0.dist-info/top_level.txt
meinkonfig-0.1.0.dist-info/RECORD
