Metadata-Version: 2.1
Name: meinkonfig
Version: 0.1.0
Summary: YAML config reader
Home-page: https://github.com/vodyanoy420/meinkonfig
Author: vodyanoy
Author-email: vodyanoy420@gmail.com
Maintainer: vodyanoy
Maintainer-email: vodyanoy420@gmail.com
License: MIT
Keywords: config,yaml,yamlconfig,meinkonfig
Platform: Linux
Platform: Unix
Platform: Mac OS
Platform: Windows
Classifier: Programming Language :: Python :: 3.11
Requires-Dist: setuptools ~=68.2.0
Requires-Dist: PyYAML ~=6.0.1
Requires-Dist: python-dotenv ~=1.0.0
Requires-Dist: pathlib ~=1.0.1
Requires-Dist: easydict ~=1.11
